randfacts/__init__.py
randfacts/__main__.py
randfacts/randfacts.py
randfacts/safe.txt
randfacts/unsafe.txt
randfacts-0.22.0.dist-info/LICENSE
randfacts-0.22.0.dist-info/METADATA
randfacts-0.22.0.dist-info/WHEEL
randfacts-0.22.0.dist-info/entry_points.txt
randfacts-0.22.0.dist-info/RECORD
